{
  "name": "Dijkstra’s Algorithm",
  "slug": "dijkstras-algorithm",
  "category": "Graph Theory",
  "description": "A greedy algorithm that finds the shortest path from a single source vertex to all other vertices in a graph with non-negative edge weights.",
  "tags": [
    "graph",
    "shortest-path",
    "greedy",
    "priority-queue"
  ],
  "difficulty": "Medium",
  "time_complexity": {
    "best": "O(V + E log V)",
    "average": "O(V + E log V)",
    "worst": "O(V^2)"
  },
  "space_complexity": "O(V)",
  "explanation": "## Overview\r\n**Dijkstra's Algorithm** is the gold standard for finding the shortest path between nodes in a graph. It is a \"single-source\" shortest path algorithm, meaning it calculates the distance from one starting point to every other reachable node. It is famously used in network routing protocols and mapping software. Note that it only works correctly with **non-negative** edge weights.\r\n\r\n## Intuition\r\nImagine you are at a central station and want to find the quickest way to all other stations. You start by looking at your immediate neighbors and recording their distances. You then always pick the \"closest\" station you haven't visited yet, go there, and check if you can find even shorter paths to its neighbors. By always expanding from the nearest known point, you guarantee that once you \"visit\" a station, you've found the absolute shortest path to it.\r\n\r\n\r\n\r\n## How It Works\r\n1.  **Initialize**: Set the distance to the source node to 0 and all other nodes to `\\infty`. Mark all nodes as unvisited.\r\n2.  **Priority Queue**: Put all nodes into a priority queue, ordered by their current distance.\r\n3.  **Extract**: While the queue is not empty, extract the node `u` with the minimum distance.\r\n4.  **Relaxation**: For every neighbor `v` of `u` that is still unvisited:\r\n    * Calculate the tentative distance: `dist[u] + weight(u, v)`.\r\n    * If this distance is less than the currently recorded `dist[v]`, update `dist[v]` with the new value.\r\n5.  **Finalize**: Once a node is extracted from the queue, its shortest path is finalized.\r\n\r\n## Applications\r\n* **Digital Mapping**: Used in Google Maps or OpenStreetMap to find driving directions.\r\n* **IP Routing**: Used in Link State routing protocols like OSPF (Open Shortest Path First).\r\n* **Social Networks**: Finding the minimum number of connections between two users.\r\n* **Robotic Motion**: Path planning for robots to navigate obstacles in a grid.\r\n\r\n---",
  "code": {
    "cpp": "#include <vector>\r\n#include <queue>\r\n#include <climits>\r\n\r\ntypedef std::pair<int, int> pii;\r\n\r\nstd::vector<int> dijkstra(int n, int start, const std::vector<std::vector<pii>>& adj) {\r\n    std::vector<int> dist(n, INT_MAX);\r\n    std::priority_queue<pii, std::vector<pii>, std::greater<pii>> pq;\r\n\r\n    dist[start] = 0;\r\n    pq.push({0, start});\r\n\r\n    while (!pq.empty()) {\r\n        int d = pq.top().first;\r\n        int u = pq.top().second;\r\n        pq.pop();\r\n\r\n        if (d > dist[u]) continue;\r\n\r\n        for (auto& edge : adj[u]) {\r\n            int v = edge.first;\r\n            int weight = edge.second;\r\n            if (dist[u] + weight < dist[v]) {\r\n                dist[v] = dist[u] + weight;\r\n                pq.push({dist[v], v});\r\n            }\r\n        }\r\n    }\r\n    return dist;\r\n}",
    "python": "import heapq\r\n\r\ndef dijkstra(graph, start):\r\n    distances = {node: float('inf') for node in graph}\r\n    distances[start] = 0\r\n    pq = [(0, start)]\r\n\r\n    while pq:\r\n        current_distance, current_node = heapq.heappop(pq)\r\n\r\n        if current_distance > distances[current_node]:\r\n            continue\r\n\r\n        for neighbor, weight in graph[current_node].items():\r\n            distance = current_distance + weight\r\n            if distance < distances[neighbor]:\r\n                distances[neighbor] = distance\r\n                heapq.heappush(pq, (distance, neighbor))\r\n                \r\n    return distances",
    "javascript": "function dijkstra(graph, start) {\r\n    const distances = {};\r\n    const pq = new MinPriorityQueue({ priority: (res) => res.dist });\r\n\r\n    for (let node in graph) distances[node] = Infinity;\r\n    distances[start] = 0;\r\n    pq.enqueue({ node: start, dist: 0 });\r\n\r\n    while (!pq.isEmpty()) {\r\n        const { node: u, dist: d } = pq.dequeue();\r\n\r\n        if (d > distances[u]) continue;\r\n\r\n        for (let v in graph[u]) {\r\n            let weight = graph[u][v];\r\n            let newDist = distances[u] + weight;\r\n            if (newDist < distances[v]) {\r\n                distances[v] = newDist;\r\n                pq.enqueue({ node: v, dist: newDist });\r\n            }\r\n        }\r\n    }\r\n    return distances;\r\n}",
    "java": "import java.util.*;\r\n\r\npublic class Dijkstra {\r\n    public int[] solve(int n, List<List<int[]>> adj, int start) {\r\n        int[] dist = new int[n];\r\n        Arrays.fill(dist, Integer.MAX_VALUE);\r\n        dist[start] = 0;\r\n        \r\n        PriorityQueue<int[]> pq = new PriorityQueue<>(Comparator.comparingInt(a -> a[0]));\r\n        pq.add(new int[]{0, start});\r\n\r\n        while (!pq.isEmpty()) {\r\n            int[] curr = pq.poll();\r\n            int u = curr[1];\r\n\r\n            for (int[] edge : adj.get(u)) {\r\n                int v = edge[0];\r\n                int w = edge[1];\r\n                if (dist[u] + w < dist[v]) {\r\n                    dist[v] = dist[u] + w;\r\n                    pq.add(new int[]{dist[v], v});\r\n                }\r\n            }\r\n        }\r\n        return dist;\r\n    }\r\n}"
  }
}
